{"is_source_file": true, "format": "bash script", "description": "This script automates the process of restoring various types of databases (SQLite, PostgreSQL, MySQL, MongoDB) from backup files. It detects the backup type based on present files and restarts the corresponding database restore procedures accordingly.", "external_files": ["database_backup.db", "database_backup.sql", "database_backup.archive"], "external_methods": ["cp", "ls", "sudo", "pg_isready", "psql", "mysqladmin", "mysql", "mongosh", "mongorestore"], "published": [], "classes": [], "methods": [], "calls": ["cp", "ls", "sudo", "pg_isready", "psql", "mysqladmin", "mysql", "mongosh", "mongorestore"], "search-terms": ["restore_db.sh", "database restore script", "SQLite restore", "PostgreSQL restore", "MySQL restore", "MongoDB restore", "backup detection", "database backup files", "restore process"], "state": 2, "file_id": 2, "knowledge_revision": 13, "git_revision": "182e8438fb38dce43b8d9ab020c5daa9da9b7bfc", "hash": "67505395c0df4c9c001ab8f47571f3fb", "format-version": 4, "code-base-name": "project_management_database", "filename": "project_management_database/restore_db.sh", "revision_history": [{"13": "182e8438fb38dce43b8d9ab020c5daa9da9b7bfc"}]}